{"id": "cHdaL7GVYtM", "title": "Preferimos el Txu-Txu", "formats": [{"asr": 48000, "filesize": 977950, "format_id": "249", "format_note": "tiny", "fps": null, "height": null, "quality": 0, "tbr": 46.982, "url": "https://rr5---sn-0opoxu-ihvr.googlevideo.com/videoplayback?expire=1670737388&ei=ixmVY-_jPMabkwbp2qMo&ip=189.173.225.87&id=o-AIXiYDlWs23bPQzff0kz72O9GM2zQJVUx3TbwFXoF8Vb&itag=249&source=youtube&requiressl=yes&mh=C6&mm=31%2C29&mn=sn-0opoxu-ihvr%2Csn-q4fl6ns7&ms=au%2Crdu&mv=m&mvi=5&pl=24&gcr=mx&initcwndbps=811250&vprv=1&mime=audio%2Fwebm&ns=jxkg_D2r3Wex7NCDHqsDti8J&gir=yes&clen=977950&dur=166.521&lmt=1568190747558628&mt=1670715427&fvip=5&keepalive=yes&fexp=24001373%2C24007246&c=WEB&txp=1311222&n=AAdvZ-3Ebc7f2O2BJ&sparams=expire%2Cei%2Cip%2Cid%2Citag%2Csource%2Crequiressl%2Cgcr%2Cvprv%2Cmime%2Cns%2Cgir%2Cclen%2Cdur%2Clmt&lsparams=mh%2Cmm%2Cmn%2Cms%2Cmv%2Cmvi%2Cpl%2Cinitcwndbps&lsig=AG3C_xAwRQIgKXW8gqQ3VtOlQD6Nh4eMlqkruZxevHIknUFUtLp8NUACIQCWatvcmGr4TJ5g37n19oWh30M93w73Gk74coPsBjkPuQ%3D%3D&sig=AOq0QJ8wRAIgE264JoPERrWrHfLFcY8ROsdLto8WLwd1HfgmVHFuhYoCIELzS3yrz75MBJP-Pd3Rqze_v6fqMjlr5GDpFPu-H5YX", "width": null, "ext": "webm", "vcodec": "none", "acodec": "opus", "abr": 46.982, "downloader_options": {"http_chunk_size": 10485760}, "container": "webm_dash", "format": "249 - audio only (tiny)", "protocol": "https", "http_headers": {"User-Agent": "Mozilla/5.0 (Windows NT 10.0; Win64; x64) AppleWebKit/537.36 (KHTML, like Gecko) Chrome/71.0.3552.1 Safari/537.36", "Accept-Charset": "ISO-8859-1,utf-8;q=0.7,*;q=0.7", "Accept": "text/html,application/xhtml+xml,application/xml;q=0.9,*/*;q=0.8", "Accept-Encoding": "gzip, deflate", "Accept-Language": "en-us,en;q=0.5"}}, {"asr": 48000, "filesize": 1296849, "format_id": "250", "format_note": "tiny", "fps": null, "height": null, "quality": 0, "tbr": 62.303, "url": "https://rr5---sn-0opoxu-ihvr.googlevideo.com/videoplayback?expire=1670737388&ei=ixmVY-_jPMabkwbp2qMo&ip=189.173.225.87&id=o-AIXiYDlWs23bPQzff0kz72O9GM2zQJVUx3TbwFXoF8Vb&itag=250&source=youtube&requiressl=yes&mh=C6&mm=31%2C29&mn=sn-0opoxu-ihvr%2Csn-q4fl6ns7&ms=au%2Crdu&mv=m&mvi=5&pl=24&gcr=mx&initcwndbps=811250&vprv=1&mime=audio%2Fwebm&ns=jxkg_D2r3Wex7NCDHqsDti8J&gir=yes&clen=1296849&dur=166.521&lmt=1568190748284279&mt=1670715427&fvip=5&keepalive=yes&fexp=24001373%2C24007246&c=WEB&txp=1311222&n=AAdvZ-3Ebc7f2O2BJ&sparams=expire%2Cei%2Cip%2Cid%2Citag%2Csource%2Crequiressl%2Cgcr%2Cvprv%2Cmime%2Cns%2Cgir%2Cclen%2Cdur%2Clmt&lsparams=mh%2Cmm%2Cmn%2Cms%2Cmv%2Cmvi%2Cpl%2Cinitcwndbps&lsig=AG3C_xAwRQIgf5u1qX39lUwBxtI9b39Evn1qltCsZQKINdVX7j3xJfECIQDmB_DVEKpMrq8tN8uFGdJu4k5R6l3SjA-NvqzXEhDgSw%3D%3D&sig=AOq0QJ8wRgIhAKljGhk_TdguaTS0N0_GXpoaglWDg2OE4v-_cFFKs7MTAiEA_FdVQoK37CNUlgjxsJgNKIVMqOfN7I4ylVqyJ1XFZoI=", "width": null, "ext": "webm", "vcodec": "none", "acodec": "opus", "abr": 62.303, "downloader_options": {"http_chunk_size": 10485760}, "container": "webm_dash", "format": "250 - audio only (tiny)", "protocol": "https", "http_headers": {"User-Agent": "Mozilla/5.0 (Windows NT 10.0; Win64; x64) AppleWebKit/537.36 (KHTML, like Gecko) Chrome/71.0.3552.1 Safari/537.36", "Accept-Charset": "ISO-8859-1,utf-8;q=0.7,*;q=0.7", "Accept": "text/html,application/xhtml+xml,application/xml;q=0.9,*/*;q=0.8", "Accept-Encoding": "gzip, deflate", "Accept-Language": "en-us,en;q=0.5"}}, {"asr": 48000, "filesize": 2593825, "format_id": "251", "format_note": "tiny", "fps": null, "height": null, "quality": 0, "tbr": 124.612, "url": "https://rr5---sn-0opoxu-ihvr.googlevideo.com/videoplayback?expire=1670737388&ei=ixmVY-_jPMabkwbp2qMo&ip=189.173.225.87&id=o-AIXiYDlWs23bPQzff0kz72O9GM2zQJVUx3TbwFXoF8Vb&itag=251&source=youtube&requiressl=yes&mh=C6&mm=31%2C29&mn=sn-0opoxu-ihvr%2Csn-q4fl6ns7&ms=au%2Crdu&mv=m&mvi=5&pl=24&gcr=mx&initcwndbps=811250&vprv=1&mime=audio%2Fwebm&ns=jxkg_D2r3Wex7NCDHqsDti8J&gir=yes&clen=2593825&dur=166.521&lmt=1568190749214691&mt=1670715427&fvip=5&keepalive=yes&fexp=24001373%2C24007246&c=WEB&txp=1311222&n=AAdvZ-3Ebc7f2O2BJ&sparams=expire%2Cei%2Cip%2Cid%2Citag%2Csource%2Crequiressl%2Cgcr%2Cvprv%2Cmime%2Cns%2Cgir%2Cclen%2Cdur%2Clmt&lsparams=mh%2Cmm%2Cmn%2Cms%2Cmv%2Cmvi%2Cpl%2Cinitcwndbps&lsig=AG3C_xAwRQIhAMffTIW5-lTKSxbnKdLXQp2Oii-13i0QPmbF02ynp9x1AiAt1xOXoItPLDDgOjnLtAoD-M0PwZtz0vod_PTDsiSxIA%3D%3D&sig=AOq0QJ8wRQIgSQB2FBXadYbKoZSER2i1ZS-F7CoqpUm6yJdzWAZ20NICIQCYoI8vIJgkb--FcrJsDym4E-HqMyrgXLpUegXQ0LmTVA==", "width": null, "ext": "webm", "vcodec": "none", "acodec": "opus", "abr": 124.612, "downloader_options": {"http_chunk_size": 10485760}, "container": "webm_dash", "format": "251 - audio only (tiny)", "protocol": "https", "http_headers": {"User-Agent": "Mozilla/5.0 (Windows NT 10.0; Win64; x64) AppleWebKit/537.36 (KHTML, like Gecko) Chrome/71.0.3552.1 Safari/537.36", "Accept-Charset": "ISO-8859-1,utf-8;q=0.7,*;q=0.7", "Accept": "text/html,application/xhtml+xml,application/xml;q=0.9,*/*;q=0.8", "Accept-Encoding": "gzip, deflate", "Accept-Language": "en-us,en;q=0.5"}}, {"asr": 44100, "filesize": 2697439, "format_id": "140", "format_note": "tiny", "fps": null, "height": null, "quality": 0, "tbr": 129.603, "url": "https://rr5---sn-0opoxu-ihvr.googlevideo.com/videoplayback?expire=1670737388&ei=ixmVY-_jPMabkwbp2qMo&ip=189.173.225.87&id=o-AIXiYDlWs23bPQzff0kz72O9GM2zQJVUx3TbwFXoF8Vb&itag=140&source=youtube&requiressl=yes&mh=C6&mm=31%2C29&mn=sn-0opoxu-ihvr%2Csn-q4fl6ns7&ms=au%2Crdu&mv=m&mvi=5&pl=24&gcr=mx&initcwndbps=811250&vprv=1&mime=audio%2Fmp4&ns=jxkg_D2r3Wex7NCDHqsDti8J&gir=yes&clen=2697439&dur=166.504&lmt=1601814837623008&mt=1670715427&fvip=5&keepalive=yes&fexp=24001373%2C24007246&c=WEB&txp=1311222&n=AAdvZ-3Ebc7f2O2BJ&sparams=expire%2Cei%2Cip%2Cid%2Citag%2Csource%2Crequiressl%2Cgcr%2Cvprv%2Cmime%2Cns%2Cgir%2Cclen%2Cdur%2Clmt&lsparams=mh%2Cmm%2Cmn%2Cms%2Cmv%2Cmvi%2Cpl%2Cinitcwndbps&lsig=AG3C_xAwRgIhAJaQL9f4f9-0t4d9RxtZR4Y7r0M2fa3SNVGl7E2uo4dkAiEAq4G8Kf4wmoTPry15pQp4GiIvHMu2w87iIq8zQ14fNEQ%3D&sig=AOq0QJ8wRAIgZDFmO4dNfvsg81GLoVHu2-QLz5OodojMWIoa94-4-a4CIEIXDEQzo5VNpnD9b-1flNAun-WkZdhGBgACXrHf6Ov7", "width": null, "ext": "m4a", "vcodec": "none", "acodec": "mp4a.40.2", "abr": 129.603, "downloader_options": {"http_chunk_size": 10485760}, "container": "m4a_dash", "format": "140 - audio only (tiny)", "protocol": "https", "http_headers": {"User-Agent": "Mozilla/5.0 (Windows NT 10.0; Win64; x64) AppleWebKit/537.36 (KHTML, like Gecko) Chrome/71.0.3552.1 Safari/537.36", "Accept-Charset": "ISO-8859-1,utf-8;q=0.7,*;q=0.7", "Accept": "text/html,application/xhtml+xml,application/xml;q=0.9,*/*;q=0.8", "Accept-Encoding": "gzip, deflate", "Accept-Language": "en-us,en;q=0.5"}}, {"asr": null, "filesize": 223559, "format_id": "160", "format_note": "144p", "fps": 25, "height": 144, "quality": 0, "tbr": 10.742, "url": "https://rr5---sn-0opoxu-ihvr.googlevideo.com/videoplayback?expire=1670737388&ei=ixmVY-_jPMabkwbp2qMo&ip=189.173.225.87&id=o-AIXiYDlWs23bPQzff0kz72O9GM2zQJVUx3TbwFXoF8Vb&itag=160&aitags=133%2C134%2C135%2C136%2C137%2C160%2C242%2C243%2C244%2C247%2C248%2C278&source=youtube&requiressl=yes&mh=C6&mm=31%2C29&mn=sn-0opoxu-ihvr%2Csn-q4fl6ns7&ms=au%2Crdu&mv=m&mvi=5&pl=24&gcr=mx&initcwndbps=811250&vprv=1&mime=video%2Fmp4&ns=jxkg_D2r3Wex7NCDHqsDti8J&gir=yes&clen=223559&dur=166.480&lmt=1601815059370147&mt=1670715427&fvip=5&keepalive=yes&fexp=24001373%2C24007246&c=WEB&txp=1311222&n=AAdvZ-3Ebc7f2O2BJ&sparams=expire%2Cei%2Cip%2Cid%2Caitags%2Csource%2Crequiressl%2Cgcr%2Cvprv%2Cmime%2Cns%2Cgir%2Cclen%2Cdur%2Clmt&lsparams=mh%2Cmm%2Cmn%2Cms%2Cmv%2Cmvi%2Cpl%2Cinitcwndbps&lsig=AG3C_xAwRQIhAKqQruVuP778HLNgJRRdm0GOTQgcePu_y9DJCBtDKco8AiBSRRZbT01rHzATF2XD1Mdx_zbnUwHJzNxi8BBBez7jgw%3D%3D&sig=AOq0QJ8wRQIgOiAIMMnojD1NW7WcaTrTc4ZpODZSeWYhgPhD-zU9UjgCIQCBsqrTHkO7UNOZtqEirkuZ5crt_PxhtG9GzquQ7yHW4Q==", "width": 144, "ext": "mp4", "vcodec": "avc1.4d400b", "acodec": "none", "vbr": 10.742, "downloader_options": {"http_chunk_size": 10485760}, "container": "mp4_dash", "format": "160 - 144x144 (144p)", "protocol": "https", "http_headers": {"User-Agent": "Mozilla/5.0 (Windows NT 10.0; Win64; x64) AppleWebKit/537.36 (KHTML, like Gecko) Chrome/71.0.3552.1 Safari/537.36", "Accept-Charset": "ISO-8859-1,utf-8;q=0.7,*;q=0.7", "Accept": "text/html,application/xhtml+xml,application/xml;q=0.9,*/*;q=0.8", "Accept-Encoding": "gzip, deflate", "Accept-Language": "en-us,en;q=0.5"}}, {"asr": null, "filesize": 507009, "format_id": "278", "format_note": "144p", "fps": 25, "height": 144, "quality": 0, "tbr": 24.363, "url": "https://rr5---sn-0opoxu-ihvr.googlevideo.com/videoplayback?expire=1670737388&ei=ixmVY-_jPMabkwbp2qMo&ip=189.173.225.87&id=o-AIXiYDlWs23bPQzff0kz72O9GM2zQJVUx3TbwFXoF8Vb&itag=278&aitags=133%2C134%2C135%2C136%2C137%2C160%2C242%2C243%2C244%2C247%2C248%2C278&source=youtube&requiressl=yes&mh=C6&mm=31%2C29&mn=sn-0opoxu-ihvr%2Csn-q4fl6ns7&ms=au%2Crdu&mv=m&mvi=5&pl=24&gcr=mx&initcwndbps=811250&vprv=1&mime=video%2Fwebm&ns=jxkg_D2r3Wex7NCDHqsDti8J&gir=yes&clen=507009&dur=166.480&lmt=1601819423694107&mt=1670715427&fvip=5&keepalive=yes&fexp=24001373%2C24007246&c=WEB&txp=1311222&n=AAdvZ-3Ebc7f2O2BJ&sparams=expire%2Cei%2Cip%2Cid%2Caitags%2Csource%2Crequiressl%2Cgcr%2Cvprv%2Cmime%2Cns%2Cgir%2Cclen%2Cdur%2Clmt&lsparams=mh%2Cmm%2Cmn%2Cms%2Cmv%2Cmvi%2Cpl%2Cinitcwndbps&lsig=AG3C_xAwRQIgfHT4nljlt66rNGU3ydhPRA9HCgnegcQHNdHkpjCcBD8CIQDg2nGrJsBAKjzSDnxRBmzmPHt1_PjsM4FL4vg_OVRixg%3D%3D&sig=AOq0QJ8wRQIgdYPr4tZX-TdAjwUz35QjFWFaCcKCBUyXoT_QaZz-V90CIQDcWmVzNup3x_ZFPbL90G1Ei9-PZvegCCZLlnQKs3qvMQ==", "width": 144, "ext": "webm", "vcodec": "vp9", "acodec": "none", "vbr": 24.363, "downloader_options": {"http_chunk_size": 10485760}, "container": "webm_dash", "format": "278 - 144x144 (144p)", "protocol": "https", "http_headers": {"User-Agent": "Mozilla/5.0 (Windows NT 10.0; Win64; x64) AppleWebKit/537.36 (KHTML, like Gecko) Chrome/71.0.3552.1 Safari/537.36", "Accept-Charset": "ISO-8859-1,utf-8;q=0.7,*;q=0.7", "Accept": "text/html,application/xhtml+xml,application/xml;q=0.9,*/*;q=0.8", "Accept-Encoding": "gzip, deflate", "Accept-Language": "en-us,en;q=0.5"}}, {"asr": null, "filesize": 383097, "format_id": "133", "format_note": "240p", "fps": 25, "height": 240, "quality": 1, "tbr": 18.409, "url": "https://rr5---sn-0opoxu-ihvr.googlevideo.com/videoplayback?expire=1670737388&ei=ixmVY-_jPMabkwbp2qMo&ip=189.173.225.87&id=o-AIXiYDlWs23bPQzff0kz72O9GM2zQJVUx3TbwFXoF8Vb&itag=133&aitags=133%2C134%2C135%2C136%2C137%2C160%2C242%2C243%2C244%2C247%2C248%2C278&source=youtube&requiressl=yes&mh=C6&mm=31%2C29&mn=sn-0opoxu-ihvr%2Csn-q4fl6ns7&ms=au%2Crdu&mv=m&mvi=5&pl=24&gcr=mx&initcwndbps=811250&vprv=1&mime=video%2Fmp4&ns=jxkg_D2r3Wex7NCDHqsDti8J&gir=yes&clen=383097&dur=166.480&lmt=1601815059392697&mt=1670715427&fvip=5&keepalive=yes&fexp=24001373%2C24007246&c=WEB&txp=1311222&n=AAdvZ-3Ebc7f2O2BJ&sparams=expire%2Cei%2Cip%2Cid%2Caitags%2Csource%2Crequiressl%2Cgcr%2Cvprv%2Cmime%2Cns%2Cgir%2Cclen%2Cdur%2Clmt&lsparams=mh%2Cmm%2Cmn%2Cms%2Cmv%2Cmvi%2Cpl%2Cinitcwndbps&lsig=AG3C_xAwRAIgBYBr2L_NUbbp_rMAvMPFCcLBsvttbgTOjDPrwx6GH_MCIFNEMnMRreSZbpMn0-qpzhyHuo8zjO8AStzHRWk1n2Tu&sig=AOq0QJ8wRQIhAPsEU3QL4PIXVPVc4p188lx2NUBxMcZw-sDgKdqhCoWUAiAVGecmIYBbamZMzvNeWShsyOjCSnyk5L60imxaxtFqSg==", "width": 240, "ext": "mp4", "vcodec": "avc1.4d400c", "acodec": "none", "vbr": 18.409, "downloader_options": {"http_chunk_size": 10485760}, "container": "mp4_dash", "format": "133 - 240x240 (240p)", "protocol": "https", "http_headers": {"User-Agent": "Mozilla/5.0 (Windows NT 10.0; Win64; x64) AppleWebKit/537.36 (KHTML, like Gecko) Chrome/71.0.3552.1 Safari/537.36", "Accept-Charset": "ISO-8859-1,utf-8;q=0.7,*;q=0.7", "Accept": "text/html,application/xhtml+xml,application/xml;q=0.9,*/*;q=0.8", "Accept-Encoding": "gzip, deflate", "Accept-Language": "en-us,en;q=0.5"}}, {"asr": null, "filesize": 1073447, "format_id": "242", "format_note": "240p", "fps": 25, "height": 240, "quality": 1, "tbr": 51.583, "url": "https://rr5---sn-0opoxu-ihvr.googlevideo.com/videoplayback?expire=1670737388&ei=ixmVY-_jPMabkwbp2qMo&ip=189.173.225.87&id=o-AIXiYDlWs23bPQzff0kz72O9GM2zQJVUx3TbwFXoF8Vb&itag=242&aitags=133%2C134%2C135%2C136%2C137%2C160%2C242%2C243%2C244%2C247%2C248%2C278&source=youtube&requiressl=yes&mh=C6&mm=31%2C29&mn=sn-0opoxu-ihvr%2Csn-q4fl6ns7&ms=au%2Crdu&mv=m&mvi=5&pl=24&gcr=mx&initcwndbps=811250&vprv=1&mime=video%2Fwebm&ns=jxkg_D2r3Wex7NCDHqsDti8J&gir=yes&clen=1073447&dur=166.480&lmt=1601819423588720&mt=1670715427&fvip=5&keepalive=yes&fexp=24001373%2C24007246&c=WEB&txp=1311222&n=AAdvZ-3Ebc7f2O2BJ&sparams=expire%2Cei%2Cip%2Cid%2Caitags%2Csource%2Crequiressl%2Cgcr%2Cvprv%2Cmime%2Cns%2Cgir%2Cclen%2Cdur%2Clmt&lsparams=mh%2Cmm%2Cmn%2Cms%2Cmv%2Cmvi%2Cpl%2Cinitcwndbps&lsig=AG3C_xAwRgIhANKeEuAKRtVJ1k3qhEg22sfi3a-X9dV-pacq-TPsdc_gAiEAofRhwf2e4AJlpdsPSob7M2_j9emIAvn___I4iwlesrE%3D&sig=AOq0QJ8wRAIgIY6DgtdKiVBtzAlyCIgsi4NV2_j5VHdJH8e00i7rk30CIG2qNZuzQu3IhySYghI0A7LjT29IJEl9LynI9FHimFiG", "width": 240, "ext": "webm", "vcodec": "vp9", "acodec": "none", "vbr": 51.583, "downloader_options": {"http_chunk_size": 10485760}, "container": "webm_dash", "format": "242 - 240x240 (240p)", "protocol": "https", "http_headers": {"User-Agent": "Mozilla/5.0 (Windows NT 10.0; Win64; x64) AppleWebKit/537.36 (KHTML, like Gecko) Chrome/71.0.3552.1 Safari/537.36", "Accept-Charset": "ISO-8859-1,utf-8;q=0.7,*;q=0.7", "Accept": "text/html,application/xhtml+xml,application/xml;q=0.9,*/*;q=0.8", "Accept-Encoding": "gzip, deflate", "Accept-Language": "en-us,en;q=0.5"}}, {"asr": null, "filesize": 535476, "format_id": "134", "format_note": "360p", "fps": 25, "height": 360, "quality": 2, "tbr": 25.731, "url": "https://rr5---sn-0opoxu-ihvr.googlevideo.com/videoplayback?expire=1670737388&ei=ixmVY-_jPMabkwbp2qMo&ip=189.173.225.87&id=o-AIXiYDlWs23bPQzff0kz72O9GM2zQJVUx3TbwFXoF8Vb&itag=134&aitags=133%2C134%2C135%2C136%2C137%2C160%2C242%2C243%2C244%2C247%2C248%2C278&source=youtube&requiressl=yes&mh=C6&mm=31%2C29&mn=sn-0opoxu-ihvr%2Csn-q4fl6ns7&ms=au%2Crdu&mv=m&mvi=5&pl=24&gcr=mx&initcwndbps=811250&vprv=1&mime=video%2Fmp4&ns=jxkg_D2r3Wex7NCDHqsDti8J&gir=yes&clen=535476&dur=166.480&lmt=1601815059401355&mt=1670715427&fvip=5&keepalive=yes&fexp=24001373%2C24007246&c=WEB&txp=1311222&n=AAdvZ-3Ebc7f2O2BJ&sparams=expire%2Cei%2Cip%2Cid%2Caitags%2Csource%2Crequiressl%2Cgcr%2Cvprv%2Cmime%2Cns%2Cgir%2Cclen%2Cdur%2Clmt&lsparams=mh%2Cmm%2Cmn%2Cms%2Cmv%2Cmvi%2Cpl%2Cinitcwndbps&lsig=AG3C_xAwRQIgXNfA8r1w6EdmbHGh4yeP4ecNCVOBBNS2yVOQ1buo8vUCIQCCMMPNZUWQhgZgsPhL3AE6Q-CgHeIvfY02fZHDp73P7A%3D%3D&sig=AOq0QJ8wRQIgVAnKBqVYvMDOvPUWsGMLR1787uPiF5hB_WoGvQMaYSACIQCCtWZDMXZTfRrML915_92oHNDulRdcHicERy1vijQahg==", "width": 360, "ext": "mp4", "vcodec": "avc1.4d4015", "acodec": "none", "vbr": 25.731, "downloader_options": {"http_chunk_size": 10485760}, "container": "mp4_dash", "format": "134 - 360x360 (360p)", "protocol": "https", "http_headers": {"User-Agent": "Mozilla/5.0 (Windows NT 10.0; Win64; x64) AppleWebKit/537.36 (KHTML, like Gecko) Chrome/71.0.3552.1 Safari/537.36", "Accept-Charset": "ISO-8859-1,utf-8;q=0.7,*;q=0.7", "Accept": "text/html,application/xhtml+xml,application/xml;q=0.9,*/*;q=0.8", "Accept-Encoding": "gzip, deflate", "Accept-Language": "en-us,en;q=0.5"}}, {"asr": null, "filesize": 1824014, "format_id": "243", "format_note": "360p", "fps": 25, "height": 360, "quality": 2, "tbr": 87.65, "url": "https://rr5---sn-0opoxu-ihvr.googlevideo.com/videoplayback?expire=1670737388&ei=ixmVY-_jPMabkwbp2qMo&ip=189.173.225.87&id=o-AIXiYDlWs23bPQzff0kz72O9GM2zQJVUx3TbwFXoF8Vb&itag=243&aitags=133%2C134%2C135%2C136%2C137%2C160%2C242%2C243%2C244%2C247%2C248%2C278&source=youtube&requiressl=yes&mh=C6&mm=31%2C29&mn=sn-0opoxu-ihvr%2Csn-q4fl6ns7&ms=au%2Crdu&mv=m&mvi=5&pl=24&gcr=mx&initcwndbps=811250&vprv=1&mime=video%2Fwebm&ns=jxkg_D2r3Wex7NCDHqsDti8J&gir=yes&clen=1824014&dur=166.480&lmt=1601819423583148&mt=1670715427&fvip=5&keepalive=yes&fexp=24001373%2C24007246&c=WEB&txp=1311222&n=AAdvZ-3Ebc7f2O2BJ&sparams=expire%2Cei%2Cip%2Cid%2Caitags%2Csource%2Crequiressl%2Cgcr%2Cvprv%2Cmime%2Cns%2Cgir%2Cclen%2Cdur%2Clmt&lsparams=mh%2Cmm%2Cmn%2Cms%2Cmv%2Cmvi%2Cpl%2Cinitcwndbps&lsig=AG3C_xAwRAIgIrTF8sf18DCHnmChp2rk66AGNM2TISz1nx7uAzxRxFoCID0A-kQwzWd9fJ9Id73JScpLla4ihCyOL-xTL9IRXlCL&sig=AOq0QJ8wRQIhAJCFJghHuI0KO43vMspSEF-fJsSR57FkP0Tc9sm5yw3WAiAT8jMkv8WWBhMkIFiJSzE55ieTNwlGwwhVJflPokcWzA==", "width": 360, "ext": "webm", "vcodec": "vp9", "acodec": "none", "vbr": 87.65, "downloader_options": {"http_chunk_size": 10485760}, "container": "webm_dash", "format": "243 - 360x360 (360p)", "protocol": "https", "http_headers": {"User-Agent": "Mozilla/5.0 (Windows NT 10.0; Win64; x64) AppleWebKit/537.36 (KHTML, like Gecko) Chrome/71.0.3552.1 Safari/537.36", "Accept-Charset": "ISO-8859-1,utf-8;q=0.7,*;q=0.7", "Accept": "text/html,application/xhtml+xml,application/xml;q=0.9,*/*;q=0.8", "Accept-Encoding": "gzip, deflate", "Accept-Language": "en-us,en;q=0.5"}}, {"asr": null, "filesize": 986116, "format_id": "135", "format_note": "480p", "fps": 25, "height": 480, "quality": 3, "tbr": 47.386, "url": "https://rr5---sn-0opoxu-ihvr.googlevideo.com/videoplayback?expire=1670737388&ei=ixmVY-_jPMabkwbp2qMo&ip=189.173.225.87&id=o-AIXiYDlWs23bPQzff0kz72O9GM2zQJVUx3TbwFXoF8Vb&itag=135&aitags=133%2C134%2C135%2C136%2C137%2C160%2C242%2C243%2C244%2C247%2C248%2C278&source=youtube&requiressl=yes&mh=C6&mm=31%2C29&mn=sn-0opoxu-ihvr%2Csn-q4fl6ns7&ms=au%2Crdu&mv=m&mvi=5&pl=24&gcr=mx&initcwndbps=811250&vprv=1&mime=video%2Fmp4&ns=jxkg_D2r3Wex7NCDHqsDti8J&gir=yes&clen=986116&dur=166.480&lmt=1601815059370323&mt=1670715427&fvip=5&keepalive=yes&fexp=24001373%2C24007246&c=WEB&txp=1311222&n=AAdvZ-3Ebc7f2O2BJ&sparams=expire%2Cei%2Cip%2Cid%2Caitags%2Csource%2Crequiressl%2Cgcr%2Cvprv%2Cmime%2Cns%2Cgir%2Cclen%2Cdur%2Clmt&lsparams=mh%2Cmm%2Cmn%2Cms%2Cmv%2Cmvi%2Cpl%2Cinitcwndbps&lsig=AG3C_xAwRAIgV4j3ZRgDDEBUJ8vGAqb2pvcANEBjd5ekVmsEOARpvBACIDD2U_Dj1PUHAm3FrpUTfrIRvdvMFzHFxvF4OPo5Ipzt&sig=AOq0QJ8wRQIhAJJTD4sghUCpNnwKUd29AXatHLW5HeaEvzd2OP25TxFAAiAYeUFWY9gWhfxnVh6RjaGBu2n-igslMMyQmOZ9Obf4jg==", "width": 480, "ext": "mp4", "vcodec": "avc1.4d401e", "acodec": "none", "vbr": 47.386, "downloader_options": {"http_chunk_size": 10485760}, "container": "mp4_dash", "format": "135 - 480x480 (480p)", "protocol": "https", "http_headers": {"User-Agent": "Mozilla/5.0 (Windows NT 10.0; Win64; x64) AppleWebKit/537.36 (KHTML, like Gecko) Chrome/71.0.3552.1 Safari/537.36", "Accept-Charset": "ISO-8859-1,utf-8;q=0.7,*;q=0.7", "Accept": "text/html,application/xhtml+xml,application/xml;q=0.9,*/*;q=0.8", "Accept-Encoding": "gzip, deflate", "Accept-Language": "en-us,en;q=0.5"}}, {"asr": null, "filesize": 3253419, "format_id": "244", "format_note": "480p", "fps": 25, "height": 480, "quality": 3, "tbr": 156.339, "url": "https://rr5---sn-0opoxu-ihvr.googlevideo.com/videoplayback?expire=1670737388&ei=ixmVY-_jPMabkwbp2qMo&ip=189.173.225.87&id=o-AIXiYDlWs23bPQzff0kz72O9GM2zQJVUx3TbwFXoF8Vb&itag=244&aitags=133%2C134%2C135%2C136%2C137%2C160%2C242%2C243%2C244%2C247%2C248%2C278&source=youtube&requiressl=yes&mh=C6&mm=31%2C29&mn=sn-0opoxu-ihvr%2Csn-q4fl6ns7&ms=au%2Crdu&mv=m&mvi=5&pl=24&gcr=mx&initcwndbps=811250&vprv=1&mime=video%2Fwebm&ns=jxkg_D2r3Wex7NCDHqsDti8J&gir=yes&clen=3253419&dur=166.480&lmt=1601819423752025&mt=1670715427&fvip=5&keepalive=yes&fexp=24001373%2C24007246&c=WEB&txp=1311222&n=AAdvZ-3Ebc7f2O2BJ&sparams=expire%2Cei%2Cip%2Cid%2Caitags%2Csource%2Crequiressl%2Cgcr%2Cvprv%2Cmime%2Cns%2Cgir%2Cclen%2Cdur%2Clmt&lsparams=mh%2Cmm%2Cmn%2Cms%2Cmv%2Cmvi%2Cpl%2Cinitcwndbps&lsig=AG3C_xAwRQIgZAeGGYO13J4jWRc6P71Lsj-pS8IfBKQiuujKdPEkAqYCIQC7QzaZhDpFPE6zdLnfRAkzDvlSFS04sxcnHvtvrJrLZg%3D%3D&sig=AOq0QJ8wRQIhANeKhf87EFbSxWUUeTlbxj_kLo8oqDI4n-Jy-w9y1W_oAiAf7MALWRm8CRnVhbuBw3HKfgZ758eujqhYpgxbQ0KY0g==", "width": 480, "ext": "webm", "vcodec": "vp9", "acodec": "none", "vbr": 156.339, "downloader_options": {"http_chunk_size": 10485760}, "container": "webm_dash", "format": "244 - 480x480 (480p)", "protocol": "https", "http_headers": {"User-Agent": "Mozilla/5.0 (Windows NT 10.0; Win64; x64) AppleWebKit/537.36 (KHTML, like Gecko) Chrome/71.0.3552.1 Safari/537.36", "Accept-Charset": "ISO-8859-1,utf-8;q=0.7,*;q=0.7", "Accept": "text/html,application/xhtml+xml,application/xml;q=0.9,*/*;q=0.8", "Accept-Encoding": "gzip, deflate", "Accept-Language": "en-us,en;q=0.5"}}, {"asr": null, "filesize": 1855197, "format_id": "136", "format_note": "720p", "fps": 25, "height": 720, "quality": 4, "tbr": 89.149, "url": "https://rr5---sn-0opoxu-ihvr.googlevideo.com/videoplayback?expire=1670737388&ei=ixmVY-_jPMabkwbp2qMo&ip=189.173.225.87&id=o-AIXiYDlWs23bPQzff0kz72O9GM2zQJVUx3TbwFXoF8Vb&itag=136&aitags=133%2C134%2C135%2C136%2C137%2C160%2C242%2C243%2C244%2C247%2C248%2C278&source=youtube&requiressl=yes&mh=C6&mm=31%2C29&mn=sn-0opoxu-ihvr%2Csn-q4fl6ns7&ms=au%2Crdu&mv=m&mvi=5&pl=24&gcr=mx&initcwndbps=811250&vprv=1&mime=video%2Fmp4&ns=jxkg_D2r3Wex7NCDHqsDti8J&gir=yes&clen=1855197&dur=166.480&lmt=1601815059626461&mt=1670715427&fvip=5&keepalive=yes&fexp=24001373%2C24007246&c=WEB&txp=1311222&n=AAdvZ-3Ebc7f2O2BJ&sparams=expire%2Cei%2Cip%2Cid%2Caitags%2Csource%2Crequiressl%2Cgcr%2Cvprv%2Cmime%2Cns%2Cgir%2Cclen%2Cdur%2Clmt&lsparams=mh%2Cmm%2Cmn%2Cms%2Cmv%2Cmvi%2Cpl%2Cinitcwndbps&lsig=AG3C_xAwRQIhAP84IGKImyhK3Ru2GW0fPUOe4sOCSxpX5QaGVO78GA4kAiBDUebaIBNyf6g4tRmUnU7XLnujVqmxvYmmBr6SngCKoQ%3D%3D&sig=AOq0QJ8wRQIgOjOD2-Elm0pvKC3PY1F3uhN6uxGfgqpu4vchir-Q9tkCIQDv089RUyB5GdmXiKOpX7l1qKF9gVl39XU_6K8q3o_NWg==", "width": 720, "ext": "mp4", "vcodec": "avc1.4d401f", "acodec": "none", "vbr": 89.149, "downloader_options": {"http_chunk_size": 10485760}, "container": "mp4_dash", "format": "136 - 720x720 (720p)", "protocol": "https", "http_headers": {"User-Agent": "Mozilla/5.0 (Windows NT 10.0; Win64; x64) AppleWebKit/537.36 (KHTML, like Gecko) Chrome/71.0.3552.1 Safari/537.36", "Accept-Charset": "ISO-8859-1,utf-8;q=0.7,*;q=0.7", "Accept": "text/html,application/xhtml+xml,application/xml;q=0.9,*/*;q=0.8", "Accept-Encoding": "gzip, deflate", "Accept-Language": "en-us,en;q=0.5"}}, {"asr": null, "filesize": 7715145, "format_id": "247", "format_note": "720p", "fps": 25, "height": 720, "quality": 4, "tbr": 370.742, "url": "https://rr5---sn-0opoxu-ihvr.googlevideo.com/videoplayback?expire=1670737388&ei=ixmVY-_jPMabkwbp2qMo&ip=189.173.225.87&id=o-AIXiYDlWs23bPQzff0kz72O9GM2zQJVUx3TbwFXoF8Vb&itag=247&aitags=133%2C134%2C135%2C136%2C137%2C160%2C242%2C243%2C244%2C247%2C248%2C278&source=youtube&requiressl=yes&mh=C6&mm=31%2C29&mn=sn-0opoxu-ihvr%2Csn-q4fl6ns7&ms=au%2Crdu&mv=m&mvi=5&pl=24&gcr=mx&initcwndbps=811250&vprv=1&mime=video%2Fwebm&ns=jxkg_D2r3Wex7NCDHqsDti8J&gir=yes&clen=7715145&dur=166.480&lmt=1601819423562985&mt=1670715427&fvip=5&keepalive=yes&fexp=24001373%2C24007246&c=WEB&txp=1311222&n=AAdvZ-3Ebc7f2O2BJ&sparams=expire%2Cei%2Cip%2Cid%2Caitags%2Csource%2Crequiressl%2Cgcr%2Cvprv%2Cmime%2Cns%2Cgir%2Cclen%2Cdur%2Clmt&lsparams=mh%2Cmm%2Cmn%2Cms%2Cmv%2Cmvi%2Cpl%2Cinitcwndbps&lsig=AG3C_xAwRQIhAMk4uCHeyM7b-lV43xz-Dnp9VBAQWkYHYgwsWF_yeuM1AiAc6TGFX4OPuoqsFhGwBGZ_L8oKQ1s5NGJ1MIoLKI7XYA%3D%3D&sig=AOq0QJ8wRQIgcVdRnrBw5sPqU_oGeRxrPFgAu-JEh0btwsbQxAui2tkCIQDCD3WfCptM09ICCiFPHNXkj8Hvxd9Yk3Az2z8DRBC47Q==", "width": 720, "ext": "webm", "vcodec": "vp9", "acodec": "none", "vbr": 370.742, "downloader_options": {"http_chunk_size": 10485760}, "container": "webm_dash", "format": "247 - 720x720 (720p)", "protocol": "https", "http_headers": {"User-Agent": "Mozilla/5.0 (Windows NT 10.0; Win64; x64) AppleWebKit/537.36 (KHTML, like Gecko) Chrome/71.0.3552.1 Safari/537.36", "Accept-Charset": "ISO-8859-1,utf-8;q=0.7,*;q=0.7", "Accept": "text/html,application/xhtml+xml,application/xml;q=0.9,*/*;q=0.8", "Accept-Encoding": "gzip, deflate", "Accept-Language": "en-us,en;q=0.5"}}, {"asr": null, "filesize": 5510487, "format_id": "137", "format_note": "1080p", "fps": 25, "height": 1080, "quality": 5, "tbr": 264.799, "url": "https://rr5---sn-0opoxu-ihvr.googlevideo.com/videoplayback?expire=1670737388&ei=ixmVY-_jPMabkwbp2qMo&ip=189.173.225.87&id=o-AIXiYDlWs23bPQzff0kz72O9GM2zQJVUx3TbwFXoF8Vb&itag=137&aitags=133%2C134%2C135%2C136%2C137%2C160%2C242%2C243%2C244%2C247%2C248%2C278&source=youtube&requiressl=yes&mh=C6&mm=31%2C29&mn=sn-0opoxu-ihvr%2Csn-q4fl6ns7&ms=au%2Crdu&mv=m&mvi=5&pl=24&gcr=mx&initcwndbps=811250&vprv=1&mime=video%2Fmp4&ns=jxkg_D2r3Wex7NCDHqsDti8J&gir=yes&clen=5510487&dur=166.480&lmt=1601814841261612&mt=1670715427&fvip=5&keepalive=yes&fexp=24001373%2C24007246&c=WEB&txp=1311222&n=AAdvZ-3Ebc7f2O2BJ&sparams=expire%2Cei%2Cip%2Cid%2Caitags%2Csource%2Crequiressl%2Cgcr%2Cvprv%2Cmime%2Cns%2Cgir%2Cclen%2Cdur%2Clmt&lsparams=mh%2Cmm%2Cmn%2Cms%2Cmv%2Cmvi%2Cpl%2Cinitcwndbps&lsig=AG3C_xAwRQIgEx8k6j89ZRdvO3JcblDsiABGbptvYwu7guU-U_ZVthICIQDjkssrGQ2Xh6dkbXbDKK-3gvt3CrJVefv8KSLrdGyvoA%3D%3D&sig=AOq0QJ8wRQIhANf3WIQTHnICxXaxOmjrPVnBL3QGoK2YaKB47G_CIp44AiBXE-aurkoJgLPwICk_PvbbG65fNPPkZPI8-_biigIE6A==", "width": 1080, "ext": "mp4", "vcodec": "avc1.640020", "acodec": "none", "vbr": 264.799, "downloader_options": {"http_chunk_size": 10485760}, "container": "mp4_dash", "format": "137 - 1080x1080 (1080p)", "protocol": "https", "http_headers": {"User-Agent": "Mozilla/5.0 (Windows NT 10.0; Win64; x64) AppleWebKit/537.36 (KHTML, like Gecko) Chrome/71.0.3552.1 Safari/537.36", "Accept-Charset": "ISO-8859-1,utf-8;q=0.7,*;q=0.7", "Accept": "text/html,application/xhtml+xml,application/xml;q=0.9,*/*;q=0.8", "Accept-Encoding": "gzip, deflate", "Accept-Language": "en-us,en;q=0.5"}}, {"asr": null, "filesize": 13696440, "format_id": "248", "format_note": "1080p", "fps": 25, "height": 1080, "quality": 5, "tbr": 658.166, "url": "https://rr5---sn-0opoxu-ihvr.googlevideo.com/videoplayback?expire=1670737388&ei=ixmVY-_jPMabkwbp2qMo&ip=189.173.225.87&id=o-AIXiYDlWs23bPQzff0kz72O9GM2zQJVUx3TbwFXoF8Vb&itag=248&aitags=133%2C134%2C135%2C136%2C137%2C160%2C242%2C243%2C244%2C247%2C248%2C278&source=youtube&requiressl=yes&mh=C6&mm=31%2C29&mn=sn-0opoxu-ihvr%2Csn-q4fl6ns7&ms=au%2Crdu&mv=m&mvi=5&pl=24&gcr=mx&initcwndbps=811250&vprv=1&mime=video%2Fwebm&ns=jxkg_D2r3Wex7NCDHqsDti8J&gir=yes&clen=13696440&dur=166.480&lmt=1601816434601575&mt=1670715427&fvip=5&keepalive=yes&fexp=24001373%2C24007246&c=WEB&txp=1311222&n=AAdvZ-3Ebc7f2O2BJ&sparams=expire%2Cei%2Cip%2Cid%2Caitags%2Csource%2Crequiressl%2Cgcr%2Cvprv%2Cmime%2Cns%2Cgir%2Cclen%2Cdur%2Clmt&lsparams=mh%2Cmm%2Cmn%2Cms%2Cmv%2Cmvi%2Cpl%2Cinitcwndbps&lsig=AG3C_xAwRgIhAOm_w2HGWfJ32joF_eAs5PKVKfx8eqRHho2YPiccdINHAiEA64_1Yiz8_A9vQE_6Avq7Epd2jI5ITYURMKXw41ptlAE%3D&sig=AOq0QJ8wRgIhANUD4Jht8S9arbhWTSVmj4UW9RbJdaVnEezh3JQld6w0AiEAlhISvDNNjawdHhhMTbT1r3vQ65sgdDlAf7vWZZ6x8t0=", "width": 1080, "ext": "webm", "vcodec": "vp9", "acodec": "none", "vbr": 658.166, "downloader_options": {"http_chunk_size": 10485760}, "container": "webm_dash", "format": "248 - 1080x1080 (1080p)", "protocol": "https", "http_headers": {"User-Agent": "Mozilla/5.0 (Windows NT 10.0; Win64; x64) AppleWebKit/537.36 (KHTML, like Gecko) Chrome/71.0.3552.1 Safari/537.36", "Accept-Charset": "ISO-8859-1,utf-8;q=0.7,*;q=0.7", "Accept": "text/html,application/xhtml+xml,application/xml;q=0.9,*/*;q=0.8", "Accept-Encoding": "gzip, deflate", "Accept-Language": "en-us,en;q=0.5"}}, {"asr": 44100, "filesize": null, "format_id": "18", "format_note": "360p", "fps": 25, "height": 360, "quality": 2, "tbr": 154.672, "url": "https://rr5---sn-0opoxu-ihvr.googlevideo.com/videoplayback?expire=1670737388&ei=ixmVY-_jPMabkwbp2qMo&ip=189.173.225.87&id=o-AIXiYDlWs23bPQzff0kz72O9GM2zQJVUx3TbwFXoF8Vb&itag=18&source=youtube&requiressl=yes&mh=C6&mm=31%2C29&mn=sn-0opoxu-ihvr%2Csn-q4fl6ns7&ms=au%2Crdu&mv=m&mvi=5&pl=24&gcr=mx&initcwndbps=811250&vprv=1&mime=video%2Fmp4&ns=VE24B9P4Cgi3-0-hFDBbZp8J&cnr=14&ratebypass=yes&dur=166.556&lmt=1658009800517889&mt=1670715427&fvip=5&fexp=24001373%2C24007246&c=WEB&txp=1318224&n=ZttlzZvi3DF3q-2KA&sparams=expire%2Cei%2Cip%2Cid%2Citag%2Csource%2Crequiressl%2Cgcr%2Cvprv%2Cmime%2Cns%2Ccnr%2Cratebypass%2Cdur%2Clmt&lsparams=mh%2Cmm%2Cmn%2Cms%2Cmv%2Cmvi%2Cpl%2Cinitcwndbps&lsig=AG3C_xAwRAIgfHRYBv5TsHgmURa9QhueLpSQo-IM1xPAYJNoiadgW60CIHaObUtNmw414wO2fYwZwZPwyhqQqfP0B0E0UDHak3Js&sig=AOq0QJ8wRQIgKdKJVv7ruWpDMujMYZ4XcVeNHpIKVcE3kfMDsyZERmwCIQD8JNEl_nzv4Xr14Tl5fmZZ7C5ObNhZ1nfNHcmQl_7Fvg==", "width": 360, "ext": "mp4", "vcodec": "avc1.42001E", "acodec": "mp4a.40.2", "format": "18 - 360x360 (360p)", "protocol": "https", "http_headers": {"User-Agent": "Mozilla/5.0 (Windows NT 10.0; Win64; x64) AppleWebKit/537.36 (KHTML, like Gecko) Chrome/71.0.3552.1 Safari/537.36", "Accept-Charset": "ISO-8859-1,utf-8;q=0.7,*;q=0.7", "Accept": "text/html,application/xhtml+xml,application/xml;q=0.9,*/*;q=0.8", "Accept-Encoding": "gzip, deflate", "Accept-Language": "en-us,en;q=0.5"}}], "thumbnails": [{"height": 94, "url": "https://i.ytimg.com/vi/cHdaL7GVYtM/hqdefault.jpg?sqp=-oaymwEbCKgBEF5IVfKriqkDDggBFQAAiEIYAXABwAEG&rs=AOn4CLD1A_A0lqtenKLwM-d0DFKx7k5wZg", "width": 168, "resolution": "168x94", "id": "0"}, {"height": 110, "url": "https://i.ytimg.com/vi/cHdaL7GVYtM/hqdefault.jpg?sqp=-oaymwEbCMQBEG5IVfKriqkDDggBFQAAiEIYAXABwAEG&rs=AOn4CLBFe1jWXpiHen-CWqeGQpHNhFVeGw", "width": 196, "resolution": "196x110", "id": "1"}, {"height": 138, "url": "https://i.ytimg.com/vi/cHdaL7GVYtM/hqdefault.jpg?sqp=-oaymwEcCPYBEIoBSFXyq4qpAw4IARUAAIhCGAFwAcABBg==&rs=AOn4CLDAOefYZsKD33kj8s7V4W6liG6-dg", "width": 246, "resolution": "246x138", "id": "2"}, {"height": 188, "url": "https://i.ytimg.com/vi/cHdaL7GVYtM/hqdefault.jpg?sqp=-oaymwEcCNACELwBSFXyq4qpAw4IARUAAIhCGAFwAcABBg==&rs=AOn4CLD13yShFoXmmMwI94OlrU1Q9T3RtQ", "width": 336, "resolution": "336x188", "id": "3"}, {"height": 1080, "url": "https://i.ytimg.com/vi_webp/cHdaL7GVYtM/maxresdefault.webp", "width": 1920, "resolution": "1920x1080", "id": "4"}], "description": "Provided to YouTube by Routenote\n\nPreferimos el Txu-Txu \u00b7 Asto Pituak\n\nPara Bien o Para Mal As\u00ed Somos\n\n\u2117 Asto Pituak\n\nReleased on: 2017-03-14\n\nAuto-generated by YouTube.", "upload_date": "20170321", "uploader": "Asto Pituak - Topic", "uploader_id": "UCc0gxooEAYcxHJWAGrvuiBw", "uploader_url": "http://www.youtube.com/channel/UCc0gxooEAYcxHJWAGrvuiBw", "channel_id": "UCc0gxooEAYcxHJWAGrvuiBw", "channel_url": "https://www.youtube.com/channel/UCc0gxooEAYcxHJWAGrvuiBw", "duration": 167, "view_count": 3917, "average_rating": null, "age_limit": 0, "webpage_url": "https://www.youtube.com/watch?v=cHdaL7GVYtM", "categories": ["Music"], "tags": ["Asto", "Pituak", "Para", "Bien", "Mal", "As\u00ed", "Somos", "Preferimos", "el", "Txu-Txu"], "is_live": null, "album": "Para Bien o Para Mal As\u00ed Somos", "artist": "Asto Pituak", "track": "Preferimos el Txu-Txu", "release_date": "20170314", "release_year": 2017, "channel": "Asto Pituak - Topic", "creator": "Asto Pituak", "alt_title": "Preferimos el Txu-Txu", "extractor": "youtube", "webpage_url_basename": "watch", "extractor_key": "Youtube", "playlist": null, "playlist_index": null, "thumbnail": "https://i.ytimg.com/vi_webp/cHdaL7GVYtM/maxresdefault.webp", "display_id": "cHdaL7GVYtM", "asr": 44100, "filesize": null, "format_id": "18", "format_note": "360p", "fps": 25, "height": 360, "quality": 2, "tbr": 154.672, "url": "https://rr5---sn-0opoxu-ihvr.googlevideo.com/videoplayback?expire=1670737388&ei=ixmVY-_jPMabkwbp2qMo&ip=189.173.225.87&id=o-AIXiYDlWs23bPQzff0kz72O9GM2zQJVUx3TbwFXoF8Vb&itag=18&source=youtube&requiressl=yes&mh=C6&mm=31%2C29&mn=sn-0opoxu-ihvr%2Csn-q4fl6ns7&ms=au%2Crdu&mv=m&mvi=5&pl=24&gcr=mx&initcwndbps=811250&vprv=1&mime=video%2Fmp4&ns=VE24B9P4Cgi3-0-hFDBbZp8J&cnr=14&ratebypass=yes&dur=166.556&lmt=1658009800517889&mt=1670715427&fvip=5&fexp=24001373%2C24007246&c=WEB&txp=1318224&n=ZttlzZvi3DF3q-2KA&sparams=expire%2Cei%2Cip%2Cid%2Citag%2Csource%2Crequiressl%2Cgcr%2Cvprv%2Cmime%2Cns%2Ccnr%2Cratebypass%2Cdur%2Clmt&lsparams=mh%2Cmm%2Cmn%2Cms%2Cmv%2Cmvi%2Cpl%2Cinitcwndbps&lsig=AG3C_xAwRAIgfHRYBv5TsHgmURa9QhueLpSQo-IM1xPAYJNoiadgW60CIHaObUtNmw414wO2fYwZwZPwyhqQqfP0B0E0UDHak3Js&sig=AOq0QJ8wRQIgKdKJVv7ruWpDMujMYZ4XcVeNHpIKVcE3kfMDsyZERmwCIQD8JNEl_nzv4Xr14Tl5fmZZ7C5ObNhZ1nfNHcmQl_7Fvg==", "width": 360, "ext": "mp4", "vcodec": "avc1.42001E", "acodec": "mp4a.40.2", "format": "18 - 360x360 (360p)", "protocol": "https", "http_headers": {"User-Agent": "Mozilla/5.0 (Windows NT 10.0; Win64; x64) AppleWebKit/537.36 (KHTML, like Gecko) Chrome/71.0.3552.1 Safari/537.36", "Accept-Charset": "ISO-8859-1,utf-8;q=0.7,*;q=0.7", "Accept": "text/html,application/xhtml+xml,application/xml;q=0.9,*/*;q=0.8", "Accept-Encoding": "gzip, deflate", "Accept-Language": "en-us,en;q=0.5"}, "fulltitle": "Preferimos el Txu-Txu", "_filename": "Preferimos el Txu-Txu-cHdaL7GVYtM.mp4"}